onepage/__init__.py
onepage/forms.py
onepage/gv.py
onepage/models.py
onepage/template_engine.py
onepage/urls.py
onepage/utils.py
onepage/validator.py
onepage/views.py
onepage/static/onepage/action.js
onepage/static/onepage/custom.js
onepage/static/onepage/style.css
onepage/static/onepage/css/adminlte.min.css
onepage/static/onepage/css/adminlte.min.css.map
onepage/static/onepage/js/.eslintrc.json
onepage/static/onepage/js/adminlte.min.js
onepage/static/onepage/js/adminlte.min.js.map
onepage/static/onepage/js/demo.js
onepage/static/onepage/plugins/bootstrap/js/bootstrap.bundle.min.js
onepage/static/onepage/plugins/bootstrap/js/bootstrap.bundle.min.js.map
onepage/static/onepage/plugins/datatables/jquery.dataTables.min.js
onepage/static/onepage/plugins/datatables-bs4/css/dataTables.bootstrap4.min.css
onepage/static/onepage/plugins/datatables-bs4/js/dataTables.bootstrap4.min.js
onepage/static/onepage/plugins/datatables-buttons/css/buttons.bootstrap4.min.css
onepage/static/onepage/plugins/datatables-buttons/js/buttons.bootstrap4.min.js
onepage/static/onepage/plugins/datatables-buttons/js/buttons.colVis.min.js
onepage/static/onepage/plugins/datatables-buttons/js/buttons.flash.min.js
onepage/static/onepage/plugins/datatables-buttons/js/buttons.html5.min.js
onepage/static/onepage/plugins/datatables-buttons/js/buttons.print.min.js
onepage/static/onepage/plugins/datatables-buttons/js/dataTables.buttons.min.js
onepage/static/onepage/plugins/datatables-responsive/css/responsive.bootstrap4.min.css
onepage/static/onepage/plugins/datatables-responsive/js/dataTables.responsive.min.js
onepage/static/onepage/plugins/datatables-responsive/js/responsive.bootstrap4.min.js
onepage/static/onepage/plugins/fontawesome-free/css/all.min.css
onepage/static/onepage/plugins/fontawesome-free/webfonts/fa-brands-400.eot
onepage/static/onepage/plugins/fontawesome-free/webfonts/fa-brands-400.svg
onepage/static/onepage/plugins/fontawesome-free/webfonts/fa-brands-400.ttf
django_onepage-1.2.2.dist-info/METADATA
django_onepage-1.2.2.dist-info/WHEEL
django_onepage-1.2.2.dist-info/top_level.txt
django_onepage-1.2.2.dist-info/RECORD
