Metadata-Version: 2.1
Name: django-onepage
Version: 1.2.2
Summary: Django Onepage Application Management
Home-page: https://github.com/njnafir/django-onepage
Author: Nj Nafir
Author-email: njnafir@gmail.com
License: MIT
Classifier: License :: OSI Approved :: MIT License
Classifier: Programming Language :: Python :: 3
Classifier: Programming Language :: Python :: 3.8
Classifier: Programming Language :: Python :: 3.9
Requires-Dist: django
Requires-Dist: django-widget-tweaks
